nhs_dos/__init__.py
nhs_dos/cases.py
nhs_dos/config.py
nhs_dos/dispositions.py
nhs_dos/endpoints.py
nhs_dos/exceptions.py
nhs_dos/models.py
nhs_dos/payloads.py
nhs_dos/rest_api.py
nhs_dos/soap_api.py
nhs_dos/users.py
nhs_dos-0.2.0.dist-info/METADATA
nhs_dos-0.2.0.dist-info/RECORD
nhs_dos-0.2.0.dist-info/WHEEL
nhs_dos-0.2.0.dist-info/top_level.txt
