Metadata-Version: 2.1
Name: nhs-dos
Version: 0.2.0
Summary: A Python client library for interacting with the NHS Service Directory APIs
Home-page: https://github.com/nhsd-a2si/nhs-dos-py
Author: Matt Stibbs
Author-email: matt@stibbsy.co.uk
License: GNU General Public License v3
Keywords: nhs_dos
Platform: UNKNOWN
Classifier: Development Status :: 2 - Pre-Alpha
Classifier: Intended Audience :: Developers
Classifier: License :: OSI Approved :: GNU General Public License v3 (GPLv3)
Classifier: Natural Language :: English
Classifier: Programming Language :: Python :: 3
Classifier: Programming Language :: Python :: 3.6
Requires-Dist: requests
